wquart/btsnoop.cp37-win_amd64.pyd
wquart/cli.cp37-win_amd64.pyd
wquart/crc.cp37-win_amd64.pyd
wquart/decode_new.cp37-win_amd64.pyd
wquart/log.cp37-win_amd64.pyd
wquart/message_new.cp37-win_amd64.pyd
wquart/utility.cp37-win_amd64.pyd
wquart-1.0.0.4.dist-info/METADATA
wquart-1.0.0.4.dist-info/WHEEL
wquart-1.0.0.4.dist-info/top_level.txt
wquart-1.0.0.4.dist-info/RECORD
